Workbook

Sheet Dashboard
B1: DASHBOARD DE VENDAS | XBOX
B2: Receita, lucro e desempenho por período, produto, região e canal
B4: Ano: | C4: Todos | E4: Região: | F4: Todos | H4: ◄ Selecione nas células amarelas (lista suspensa) para filtrar todo o dashboard
B6: RECEITA TOTAL | E6: LUCRO TOTAL | H6: MARGEM DE LUCRO | K6: TICKET MÉDIO
B7: =Dados!Q6 -> 1003583 | E7: =Dados!Q8 -> 308359 | H7: =Dados!Q9 -> 0.30725809 | K7: =Dados!Q11 -> 1672.6383
B40: INSIGHTS (atualizam conforme os filtros)
B41: ="Produto líder: "&Dados!Q12&" — "&TEXT(Dados!Q13,"0.0%")&" da receita" -> Produto líder: Console Xbox Series S — 32.9% da receita
B42: ="Melhor mês: "&Dados!Q14 -> Melhor mês: Fev
B43: ="Região líder: "&Dados!Q15 -> Região líder: Sudeste
B44: ="Canal líder: "&Dados!Q16 -> Canal líder: Loja Online
B45: ="Unidades vendidas: "&TEXT(Dados!Q7,"#,##0")&" em "&TEXT(Dados!Q10,"#,##0")&" pedidos" -> Unidades vendidas: 1,365 em 600 pedidos
B47: Dados fictícios para fins didáticos. Fonte: aba Base_Dados (substitua pelos seus dados reais).

Sheet Base_Dados
A1: ID Pedido | B1: Data | C1: Ano | D1: Mês | E1: Produto | F1: Categoria | G1: Região | H1: Canal | I1: Quantidade | J1: Preço Unit. (R$) | K1: Custo Unit. (R$) | L1: Receita (R$) | M1: Lucro (R$) | O1: Nota
A2: PED-1002 | B2: 45623 | C2: =YEAR(B2) -> 2024 | D2: =MONTH(B2) -> 11 | E2: Cartão Presente R$100 | F2: Serviço | G2: Sudeste | H2: Loja Online | I2: 4 | J2: 100 | K2: 88 | L2: =I2*J2 -> 400 | M2: =L2-I2*K2 -> 48 | O2: Dados fictícios (valores em azul = entradas). Substitua pelas suas vendas reais mantendo as colunas; Ano, Mês, Receita e Lucro são fórmulas.
A3: PED-1003 | B3: 45840 | C3: =YEAR(B3) -> 2025 | D3: =MONTH(B3) -> 7 | E3: Console Xbox Series S | F3: Console | G3: Sul | H3: Loja Online | I3: 1 | J3: 2799 | K3: 2100 | L3: =I3*J3 -> 2799 | M3: =L3-I3*K3 -> 699
A4: PED-1004 | B4: 45380 | C4: =YEAR(B4) -> 2024 | D4: =MONTH(B4) -> 3 | E4: Controle Sem Fio | F4: Acessório | G4: Nordeste | H4: Loja Física | I4: 1 | J4: 449 | K4: 260 | L4: =I4*J4 -> 449 | M4: =L4-I4*K4 -> 189
A5: PED-1005 | B5: 45352 | C5: =YEAR(B5) -> 2024 | D5: =MONTH(B5) -> 3 | E5: Cartão Presente R$100 | F5: Serviço | G5: Sul | H5: Loja Física | I5: 1 | J5: 100 | K5: 88 | L5: =I5*J5 -> 100 | M5: =L5-I5*K5 -> 12
A6: PED-1006 | B6: 45888 | C6: =YEAR(B6) -> 2025 | D6: =MONTH(B6) -> 8 | E6: Cartão Presente R$100 | F6: Serviço | G6: Norte | H6: Loja Online | I6: 4 | J6: 100 | K6: 88 | L6: =I6*J6 -> 400 | M6: =L6-I6*K6 -> 48
A7: PED-1007 | B7: 45862 | C7: =YEAR(B7) -> 2025 | D7: =MONTH(B7) -> 7 | E7: Cartão Presente R$100 | F7: Serviço | G7: Sudeste | H7: Loja Física | I7: 3 | J7: 100 | K7: 88 | L7: =I7*J7 -> 300 | M7: =L7-I7*K7 -> 36
A8: PED-1008 | B8: 45876 | C8: =YEAR(B8) -> 2025 | D8: =MONTH(B8) -> 8 | E8: Controle Sem Fio | F8: Acessório | G8: Nordeste | H8: Loja Física | I8: 2 | J8: 449 | K8: 260 | L8: =I8*J8 -> 898 | M8: =L8-I8*K8 -> 378
A9: PED-1009 | B9: 45484 | C9: =YEAR(B9) -> 2024 | D9: =MONTH(B9) -> 7 | E9: Controle Sem Fio | F9: Acessório | G9: Sudeste | H9: Loja Física | I9: 1 | J9: 449 | K9: 260 | L9: =I9*J9 -> 449 | M9: =L9-I9*K9 -> 189
A10: PED-1010 | B10: 45800 | C10: =YEAR(B10) -> 2025 | D10: =MONTH(B10) -> 5 | E10: Game Pass Ultimate (3 meses) | F10: Serviço | G10: Sudeste | H10: Loja Física | I10: 4 | J10: 149 | K10: 60 | L10: =I10*J10 -> 596 | M10: =L10-I10*K10 -> 356
A11: PED-1011 | B11: 45756 | C11: =YEAR(B11) -> 2025 | D11: =MONTH(B11) -> 4 | E11: Controle Sem Fio | F11: Acessório | G11: Sudeste | H11: Marketplace | I11: 2 | J11: 449 | K11: 260 | L11: =I11*J11 -> 898 | M11: =L11-I11*K11 -> 378
A12: PED-1012 | B12: 45541 | C12: =YEAR(B12) -> 2024 | D12: =MONTH(B12) -> 9 | E12: Console Xbox Series S | F12: Console | G12: Sudeste | H12: Marketplace | I12: 2 | J12: 2799 | K12: 2100 | L12: =I12*J12 -> 5598 | M12: =L12-I12*K12 -> 1398
A13: PED-1013 | B13: 45751 | C13: =YEAR(B13) -> 2025 | D13: =MONTH(B13) -> 4 | E13: Controle Sem Fio | F13: Acessório | G13: Nordeste | H13: Loja Física | I13: 1 | J13: 449 | K13: 260 | L13: =I13*J13 -> 449 | M13: =L13-I13*K13 -> 189
A14: PED-1014 | B14: 45642 | C14: =YEAR(B14) -> 2024 | D14: =MONTH(B14) -> 12 | E14: Console Xbox Series S | F14: Console | G14: Sudeste | H14: Marketplace | I14: 2 | J14: 2799 | K14: 2100 | L14: =I14*J14 -> 5598 | M14: =L14-I14*K14 -> 1398
... A601: PED-1601 | B601: 45424 | C601: =YEAR(B601) -> 2024 | D601: =MONTH(B601) -> 5 | E601: Headset Xbox | F601: Acessório | G601: Nordeste | H601: Marketplace | I601: 1 | J601: 699 | K601: 420 | L601: =I601*J601 -> 699 | M601: =L601-I601*K601 -> 279

Sheet Dados
A1: Tabelas de apoio do dashboard (calculadas a partir de Base_Dados e dos filtros do Dashboard)
A2: Critério Ano | B2: =IF(Dashboard!$C$4="Todos","<>",Dashboard!$C$4) -> <>
A3: Critério Região | B3: =IF(Dashboard!$F$4="Todos","<>",Dashboard!$F$4) -> <>
A5: Nº | B5: Mês | C5: Receita | D5: Lucro | F5: Produto | G5: Receita | H5: Unidades | J5: Região | K5: Receita | M5: Canal | N5: Receita | P5: Indicador | Q5: Valor
A6: 1 | B6: Jan | C6: =SUMIFS(Base_Dados!$L$2:$L$601,Base_Dados!$D$2:$D$601,$A6,Base_Dados!$C$2:$C$601,$B$2,Base_Dados!$G$2:$G$601,$B$3) -> 102614 | D6: =SUMIFS(Base_Dados!$M$2:$M$601,Base_Dados!$D$2:$D$601,$A6,Base_Dados!$C$2:$C$601,$B$2,Base_Dados!$G$2:$G$601,$B$3) -> 29250 | F6: Console Xbox Series X | G6: =SUMIFS(Base_Dados!$L$2:$L$601,Base_Dados!$E$2:$E$601,$F6,Base_Dados!$C$2:$C$601,$B$2,Base_Dados!$G$2:$G$601,$B$3) -> 310431 | H6: =SUMIFS(Base_Dados!$I$2:$I$601,Base_Dados!$E$2:$E$601,$F6,Base_Dados!$C$2:$C$601,$B$2,Base_Dados!$G$2:$G$601,$B$3) -> 69 | J6: Norte | K6: =SUMIFS(Base_Dados!$L$2:$L$601,Base_Dados!$G$2:$G$601,$J6,Base_Dados!$C$2:$C$601,$B$2) -> 34297 | M6: Loja Online | N6: =SUMIFS(Base_Dados!$L$2:$L$601,Base_Dados!$H$2:$H$601,$M6,Base_Dados!$C$2:$C$601,$B$2,Base_Dados!$G$2:$G$601,$B$3) -> 438889 | P6: Receita total | Q6: =SUMIFS(Base_Dados!$L$2:$L$601,Base_Dados!$C$2:$C$601,$B$2,Base_Dados!$G$2:$G$601,$B$3) -> 1003583
A7: 2 | B7: Fev | C7: =SUMIFS(Base_Dados!$L$2:$L$601,Base_Dados!$D$2:$D$601,$A7,Base_Dados!$C$2:$C$601,$B$2,Base_Dados!$G$2:$G$601,$B$3) -> 113064 | D7: =SUMIFS(Base_Dados!$M$2:$M$601,Base_Dados!$D$2:$D$601,$A7,Base_Dados!$C$2:$C$601,$B$2,Base_Dados!$G$2:$G$601,$B$3) -> 32216 | F7: Console Xbox Series S | G7: =SUMIFS(Base_Dados!$L$2:$L$601,Base_Dados!$E$2:$E$601,$F7,Base_Dados!$C$2:$C$601,$B$2,Base_Dados!$G$2:$G$601,$B$3) -> 330282 | H7: =SUMIFS(Base_Dados!$I$2:$I$601,Base_Dados!$E$2:$E$601,$F7,Base_Dados!$C$2:$C$601,$B$2,Base_Dados!$G$2:$G$601,$B$3) -> 118 | J7: Nordeste | K7: =SUMIFS(Base_Dados!$L$2:$L$601,Base_Dados!$G$2:$G$601,$J7,Base_Dados!$C$2:$C$601,$B$2) -> 236967 | M7: Loja Física | N7: =SUMIFS(Base_Dados!$L$2:$L$601,Base_Dados!$H$2:$H$601,$M7,Base_Dados!$C$2:$C$601,$B$2,Base_Dados!$G$2:$G$601,$B$3) -> 287263 | P7: Unidades vendidas | Q7: =SUMIFS(Base_Dados!$I$2:$I$601,Base_Dados!$C$2:$C$601,$B$2,Base_Dados!$G$2:$G$601,$B$3) -> 1365
A8: 3 | B8: Mar | C8: =SUMIFS(Base_Dados!$L$2:$L$601,Base_Dados!$D$2:$D$601,$A8,Base_Dados!$C$2:$C$601,$B$2,Base_Dados!$G$2:$G$601,$B$3) -> 81198 | D8: =SUMIFS(Base_Dados!$M$2:$M$601,Base_Dados!$D$2:$D$601,$A8,Base_Dados!$C$2:$C$601,$B$2,Base_Dados!$G$2:$G$601,$B$3) -> 25830 | F8: Controle Sem Fio | G8: =SUMIFS(Base_Dados!$L$2:$L$601,Base_Dados!$E$2:$E$601,$F8,Base_Dados!$C$2:$C$601,$B$2,Base_Dados!$G$2:$G$601,$B$3) -> 199356 | H8: =SUMIFS(Base_Dados!$I$2:$I$601,Base_Dados!$E$2:$E$601,$F8,Base_Dados!$C$2:$C$601,$B$2,Base_Dados!$G$2:$G$601,$B$3) -> 444 | J8: Centro-Oeste | K8: =SUMIFS(Base_Dados!$L$2:$L$601,Base_Dados!$G$2:$G$601,$J8,Base_Dados!$C$2:$C$601,$B$2) -> 130570 | M8: Marketplace | N8: =SUMIFS(Base_Dados!$L$2:$L$601,Base_Dados!$H$2:$H$601,$M8,Base_Dados!$C$2:$C$601,$B$2,Base_Dados!$G$2:$G$601,$B$3) -> 277431 | P8: Lucro total | Q8: =SUMIFS(Base_Dados!$M$2:$M$601,Base_Dados!$C$2:$C$601,$B$2,Base_Dados!$G$2:$G$601,$B$3) -> 308359
A9: 4 | B9: Abr | C9: =SUMIFS(Base_Dados!$L$2:$L$601,Base_Dados!$D$2:$D$601,$A9,Base_Dados!$C$2:$C$601,$B$2,Base_Dados!$G$2:$G$601,$B$3) -> 104811 | D9: =SUMIFS(Base_Dados!$M$2:$M$601,Base_Dados!$D$2:$D$601,$A9,Base_Dados!$C$2:$C$601,$B$2,Base_Dados!$G$2:$G$601,$B$3) -> 30655 | F9: Headset Xbox | G9: =SUMIFS(Base_Dados!$L$2:$L$601,Base_Dados!$E$2:$E$601,$F9,Base_Dados!$C$2:$C$601,$B$2,Base_Dados!$G$2:$G$601,$B$3) -> 87375 | H9: =SUMIFS(Base_Dados!$I$2:$I$601,Base_Dados!$E$2:$E$601,$F9,Base_Dados!$C$2:$C$601,$B$2,Base_Dados!$G$2:$G$601,$B$3) -> 125 | J9: Sudeste | K9: =SUMIFS(Base_Dados!$L$2:$L$601,Base_Dados!$G$2:$G$601,$J9,Base_Dados!$C$2:$C$601,$B$2) -> 423154 | P9: Margem de lucro | Q9: =IFERROR(Q8/Q6,0) -> 0.30725809
A10: 5 | B10: Mai | C10: =SUMIFS(Base_Dados!$L$2:$L$601,Base_Dados!$D$2:$D$601,$A10,Base_Dados!$C$2:$C$601,$B$2,Base_Dados!$G$2:$G$601,$B$3) -> 89466 | D10: =SUMIFS(Base_Dados!$M$2:$M$601,Base_Dados!$D$2:$D$601,$A10,Base_Dados!$C$2:$C$601,$B$2,Base_Dados!$G$2:$G$601,$B$3) -> 31166 | F10: Game Pass Ultimate (3 meses) | G10: =SUMIFS(Base_Dados!$L$2:$L$601,Base_Dados!$E$2:$E$601,$F10,Base_Dados!$C$2:$C$601,$B$2,Base_Dados!$G$2:$G$601,$B$3) -> 46339 | H10: =SUMIFS(Base_Dados!$I$2:$I$601,Base_Dados!$E$2:$E$601,$F10,Base_Dados!$C$2:$C$601,$B$2,Base_Dados!$G$2:$G$601,$B$3) -> 311 | J10: Sul | K10: =SUMIFS(Base_Dados!$L$2:$L$601,Base_Dados!$G$2:$G$601,$J10,Base_Dados!$C$2:$C$601,$B$2) -> 178595 | P10: Nº de pedidos | Q10: =COUNTIFS(Base_Dados!$C$2:$C$601,$B$2,Base_Dados!$G$2:$G$601,$B$3) -> 600
A11: 6 | B11: Jun | C11: =SUMIFS(Base_Dados!$L$2:$L$601,Base_Dados!$D$2:$D$601,$A11,Base_Dados!$C$2:$C$601,$B$2,Base_Dados!$G$2:$G$601,$B$3) -> 74260 | D11: =SUMIFS(Base_Dados!$M$2:$M$601,Base_Dados!$D$2:$D$601,$A11,Base_Dados!$C$2:$C$601,$B$2,Base_Dados!$G$2:$G$601,$B$3) -> 23612 | F11: Cartão Presente R$100 | G11: =SUMIFS(Base_Dados!$L$2:$L$601,Base_Dados!$E$2:$E$601,$F11,Base_Dados!$C$2:$C$601,$B$2,Base_Dados!$G$2:$G$601,$B$3) -> 29800 | H11: =SUMIFS(Base_Dados!$I$2:$I$601,Base_Dados!$E$2:$E$601,$F11,Base_Dados!$C$2:$C$601,$B$2,Base_Dados!$G$2:$G$601,$B$3) -> 298 | P11: Ticket médio | Q11: =IFERROR(Q6/Q10,0) -> 1672.6383
A12: 7 | B12: Jul | C12: =SUMIFS(Base_Dados!$L$2:$L$601,Base_Dados!$D$2:$D$601,$A12,Base_Dados!$C$2:$C$601,$B$2,Base_Dados!$G$2:$G$601,$B$3) -> 74312 | D12: =SUMIFS(Base_Dados!$M$2:$M$601,Base_Dados!$D$2:$D$601,$A12,Base_Dados!$C$2:$C$601,$B$2,Base_Dados!$G$2:$G$601,$B$3) -> 23576 | J12: * Região ignora o filtro de Região para permitir comparação. | P12: Produto líder | Q12: =INDEX(F6:F11,MATCH(MAX(G6:G11),G6:G11,0)) -> Console Xbox Series S
A13: 8 | B13: Ago | C13: =SUMIFS(Base_Dados!$L$2:$L$601,Base_Dados!$D$2:$D$601,$A13,Base_Dados!$C$2:$C$601,$B$2,Base_Dados!$G$2:$G$601,$B$3) -> 97366 | D13: =SUMIFS(Base_Dados!$M$2:$M$601,Base_Dados!$D$2:$D$601,$A13,Base_Dados!$C$2:$C$601,$B$2,Base_Dados!$G$2:$G$601,$B$3) -> 28606 | P13: Participação do produto líder | Q13: =IFERROR(MAX(G6:G11)/Q6,0) -> 0.32910282
A14: 9 | B14: Set | C14: =SUMIFS(Base_Dados!$L$2:$L$601,Base_Dados!$D$2:$D$601,$A14,Base_Dados!$C$2:$C$601,$B$2,Base_Dados!$G$2:$G$601,$B$3) -> 69781 | D14: =SUMIFS(Base_Dados!$M$2:$M$601,Base_Dados!$D$2:$D$601,$A14,Base_Dados!$C$2:$C$601,$B$2,Base_Dados!$G$2:$G$601,$B$3) -> 20961 | P14: Melhor mês | Q14: =INDEX(B6:B17,MATCH(MAX(C6:C17),C6:C17,0)) -> Fev
A15: 10 | B15: Out | C15: =SUMIFS(Base_Dados!$L$2:$L$601,Base_Dados!$D$2:$D$601,$A15,Base_Dados!$C$2:$C$601,$B$2,Base_Dados!$G$2:$G$601,$B$3) -> 93012 | D15: =SUMIFS(Base_Dados!$M$2:$M$601,Base_Dados!$D$2:$D$601,$A15,Base_Dados!$C$2:$C$601,$B$2,Base_Dados!$G$2:$G$601,$B$3) -> 27664 | P15: Região líder | Q15: =INDEX(J6:J10,MATCH(MAX(K6:K10),K6:K10,0)) -> Sudeste
A16: 11 | B16: Nov | C16: =SUMIFS(Base_Dados!$L$2:$L$601,Base_Dados!$D$2:$D$601,$A16,Base_Dados!$C$2:$C$601,$B$2,Base_Dados!$G$2:$G$601,$B$3) -> 49885 | D16: =SUMIFS(Base_Dados!$M$2:$M$601,Base_Dados!$D$2:$D$601,$A16,Base_Dados!$C$2:$C$601,$B$2,Base_Dados!$G$2:$G$601,$B$3) -> 15689 | P16: Canal líder | Q16: =INDEX(M6:M8,MATCH(MAX(N6:N8),N6:N8,0)) -> Loja Online
A17: 12 | B17: Dez | C17: =SUMIFS(Base_Dados!$L$2:$L$601,Base_Dados!$D$2:$D$601,$A17,Base_Dados!$C$2:$C$601,$B$2,Base_Dados!$G$2:$G$601,$B$3) -> 53814 | D17: =SUMIFS(Base_Dados!$M$2:$M$601,Base_Dados!$D$2:$D$601,$A17,Base_Dados!$C$2:$C$601,$B$2,Base_Dados!$G$2:$G$601,$B$3) -> 19134
